h2o_mlops_scoring_client/VERSION
h2o_mlops_scoring_client/__init__.py
h2o_mlops_scoring_client/_configs.py
h2o_mlops_scoring_client/_utils.py
h2o_mlops_scoring_client/_version.py
h2o_mlops_scoring_client/log4j.properties
h2o_mlops_scoring_client-0.2.1b1.dist-info/METADATA
h2o_mlops_scoring_client-0.2.1b1.dist-info/WHEEL
h2o_mlops_scoring_client-0.2.1b1.dist-info/top_level.txt
h2o_mlops_scoring_client-0.2.1b1.dist-info/RECORD
