Metadata-Version: 2.1
Name: h2o-mlops-scoring-client
Version: 0.2.1b1
Summary: A Python client library to simplify robust mini-batch scoring against an H2O MLOps scoring endpoint.
Author: H2O.ai
Author-email: support@h2o.ai
License: Proprietary License
Project-URL: Documentation, https://docs.h2o.ai/mlops/mlops-scoring-client/overview
Requires-Python: >=3.8,<4
Requires-Dist: pandas <2,>=1.0.5
Requires-Dist: requests <3,>=2
Requires-Dist: urllib3 >=1.26
Provides-Extra: pyspark
Requires-Dist: pyarrow >=1 ; extra == 'pyspark'
Requires-Dist: pyspark <4,>=3 ; extra == 'pyspark'
